snakeless/__init__.py
snakeless/__main__.py
snakeless/cli_controller.py
snakeless/commands/__init__.py
snakeless/commands/check.py
snakeless/commands/deploy.py
snakeless/commands/init.py
snakeless/constants.py
snakeless/exceptions.py
snakeless/helpers.py
snakeless/mixins/__init__.py
snakeless/mixins/config_loader.py
snakeless/mixins/deployer.py
snakeless/providers/__init__.py
snakeless/providers/base.py
snakeless-0.3.0.dist-info/entry_points.txt
snakeless-0.3.0.dist-info/LICENSE
snakeless-0.3.0.dist-info/WHEEL
snakeless-0.3.0.dist-info/METADATA
snakeless-0.3.0.dist-info/RECORD
