Metadata-Version: 2.1
Name: snakeless
Version: 0.3.0
Summary: Write true serverless apps with joy
Home-page: https://github.com/Tasyp/snakeless
License: MIT
Author: German Ivanov
Author-email: germivanov@gmail.com
Requires-Python: >=3.7,<4.0
Classifier: License :: OSI Approved :: MIT License
Classifier: Programming Language :: Python :: 3
Classifier: Programming Language :: Python :: 3.7
Requires-Dist: PyYAML (>=3.13,<4.0)
Requires-Dist: cliff (>=2.14,<3.0)
Requires-Dist: fs (>=2.2,<3.0)
Requires-Dist: halo (>=0.0.21,<0.0.22)
Requires-Dist: schema (>=0.6.8,<0.7.0)
Requires-Dist: setuptools (>=39)
Project-URL: Repository, https://github.com/Tasyp/snakeless
